{"dex_no": 499, "related": [498, 499, 500], "name": "Pignite", "color": "red", "gen_no": 5, "typing": ["fire", "fighting"], "pic": "./pics/499.jpg", "anime_count": 5, "manga_count": 3, "matchups": {"0": [], "25": ["bug", "fire", "ice", "bug"], "50": ["fire", "grass", "ice", "dark", "steel", "grass", "dark", "steel"], "200": ["water", "ground", "flying", "psychic", "water", "ground", "flying", "psychic"], "400": []}, "stats": [["attack", 93], ["hp", 90], ["sp_atk", 70], ["defense", 55], ["sp_def", 55], ["speed", 55]], "stat_total": 418}