{"dex_no": 550, "related": [550, 902, 902], "name": "Basculin", "color": "green", "gen_no": 5, "typing": ["water"], "pic": "./pics/550.jpg", "anime_count": 9, "manga_count": 6, "matchups": {"0": [], "25": [], "50": ["fire", "water", "ice", "steel", "fire", "water", "ice", "steel", "fire", "water", "ice", "steel"], "200": ["electric", "grass", "electric", "grass", "electric", "grass"], "400": []}, "stats": [["speed", 98], ["attack", 92], ["sp_atk", 80], ["hp", 70], ["defense", 65], ["sp_def", 55]], "stat_total": 460}