{"dex_no": 880, "related": null, "name": "Dracozolt", "color": "green", "gen_no": 8, "typing": ["electric", "dragon"], "pic": "./pics/880.jpg", "anime_count": 1, "manga_count": 0, "matchups": {"0": ["electric"], "25": ["electric", "electric"], "50": ["fire", "water", "grass", "flying", "steel", "fire", "water", "grass", "flying", "steel", "fire", "water", "grass", "flying", "steel"], "200": ["ice", "ground", "dragon", "fairy", "ice", "ground", "dragon", "fairy", "ice", "ground", "dragon", "fairy"], "400": []}, "stats": [["attack", 100], ["hp", 90], ["defense", 90], ["sp_atk", 80], ["speed", 75], ["sp_def", 70]], "stat_total": 505}